leveldbkit
