Metadata-Version: 1.1
Name: leveldbkit
Version: 0.1.3b
Summary: An object mapper for leveldb with secondary indexes. Almost compatible with riakkit
Home-page: https://github.com/shuhaowu/leveldbkit
Author: Shuhao Wu
Author-email: shuhao@shuhaowu.com
License: LGPL
Keywords: leveldb object mapper leveldbkit database orm
Platform: UNKNOWN
Classifier: Development Status :: 4 - Beta
Classifier: License :: OSI Approved :: GNU Library or Lesser General Public License (LGPL)
Classifier: Intended Audience :: Developers
Classifier: Topic :: Database
Classifier: Topic :: Software Development :: Libraries :: Python Modules
